LICENSE
README.md
setup.py
astropy_samp_ds9/__init__.py
astropy_samp_ds9/hublauncher.py
astropy_samp_ds9/launcher.py
astropy_samp_ds9.egg-info/PKG-INFO
astropy_samp_ds9.egg-info/SOURCES.txt
astropy_samp_ds9.egg-info/dependency_links.txt
astropy_samp_ds9.egg-info/requires.txt
astropy_samp_ds9.egg-info/top_level.txt